README.md
setup.py
ovpn_server_creator_do.egg-info/PKG-INFO
ovpn_server_creator_do.egg-info/SOURCES.txt
ovpn_server_creator_do.egg-info/dependency_links.txt
ovpn_server_creator_do.egg-info/entry_points.txt
ovpn_server_creator_do.egg-info/requires.txt
ovpn_server_creator_do.egg-info/top_level.txt
ovpnserver/__init__.py
ovpnserver/main.py
ovpnserver/utils.py