Metadata-Version: 2.1
Name: ovpn-server-creator-do
Version: 0.0.1
Summary: ('OpenVPN server in Digitalocean',)
Home-page: https://github.com/NMelis/ovpn-server-creator-do
Author: NMelis
Maintainer: NMelis
License: MIT
Platform: UNKNOWN
Classifier: Development Status :: 4 - Beta
Classifier: Operating System :: OS Independent
Classifier: Intended Audience :: Developers
Classifier: Programming Language :: Python
Classifier: Programming Language :: Python :: 3
Classifier: Programming Language :: Python :: 3.4
Classifier: Programming Language :: Python :: 3.8
Classifier: Programming Language :: Python :: 3.9
Classifier: Topic :: Software Development :: Libraries
